encapsia_cli/__init__.py
encapsia_cli/completion.py
encapsia_cli/config.py
encapsia_cli/database.py
encapsia_cli/encapsia.py
encapsia_cli/fixtures.py
encapsia_cli/help.py
encapsia_cli/httpie.py
encapsia_cli/lib.py
encapsia_cli/plugininfo.py
encapsia_cli/plugins.py
encapsia_cli/run.py
encapsia_cli/s3.py
encapsia_cli/schedule.py
encapsia_cli/shell.py
encapsia_cli/token.py
encapsia_cli/users.py
encapsia_cli/version.py
encapsia_cli-0.5.12.dist-info/LICENSE
encapsia_cli-0.5.12.dist-info/METADATA
encapsia_cli-0.5.12.dist-info/WHEEL
encapsia_cli-0.5.12.dist-info/entry_points.txt
encapsia_cli-0.5.12.dist-info/RECORD
