Metadata-Version: 2.1
Name: encapsia-cli
Version: 0.5.12
Summary: Client CLI for talking to an Encapsia system.
Home-page: https://github.com/Encapsia/encapsia-cli
License: MIT
Keywords: encapsia,eSource,EDC,Clinical Trials
Author: Timothy Corbett-Clark
Author-email: timothy.corbettclark@gmail.com
Maintainer: Petre Mierluțiu
Maintainer-email: pmierlutiu@cmedtechnology.com
Requires-Python: >=3.8.1,<4.0
Classifier: License :: OSI Approved :: MIT License
Classifier: Programming Language :: Python :: 3
Classifier: Programming Language :: Python :: 3.9
Classifier: Programming Language :: Python :: 3.10
Classifier: Programming Language :: Python :: 3.11
Classifier: Programming Language :: Python :: 3.12
Provides-Extra: httpie-shell
Requires-Dist: arrow (>=1.3.0,<2.0.0)
Requires-Dist: boto3 (>=1.34.28,<2.0.0)
Requires-Dist: click (>=7.0,<8.0)
Requires-Dist: click-completion (>=0.5.0,<0.6.0)
Requires-Dist: click-shell (>=2.0,<3.0)
Requires-Dist: encapsia-api (>=0.4.5,<0.5.0)
Requires-Dist: http-prompt (>=1.0,<2.0) ; extra == "httpie-shell"
Requires-Dist: httpie (>=3.1.0,<4.0.0)
Requires-Dist: requests[security,socks] (>=2.31.0,<3.0.0)
Requires-Dist: semver (>=3.0.2,<4.0.0)
Requires-Dist: shellingham (>=1.5.4,<2.0.0)
Requires-Dist: tabulate (>=0.9.0,<0.10.0)
Requires-Dist: toml (>=0.10.2,<0.11.0)
